events_manager/__init__.py
events_manager/entities.py
events_manager/exceptions.py
events_manager/managers.py
generic_events_manager-0.0.6.dist-info/LICENSE
generic_events_manager-0.0.6.dist-info/METADATA
generic_events_manager-0.0.6.dist-info/WHEEL
generic_events_manager-0.0.6.dist-info/top_level.txt
generic_events_manager-0.0.6.dist-info/RECORD
