Metadata-Version: 2.1
Name: generic-events-manager
Version: 0.0.6
Summary: Generic class for managing events generated by an application
Home-page: UNKNOWN
Author: Tatianno Alves
Author-email: tferreiraalves@gmail.com
License: MIT License
Keywords: manager observer
Platform: UNKNOWN
Requires-Dist: wheel
